cubicweb_rodolf/__init__.py
cubicweb_rodolf/__pkginfo__.py
cubicweb_rodolf/ccplugin.py
cubicweb_rodolf/entities.py
cubicweb_rodolf/hooks.py
cubicweb_rodolf/import_data.py
cubicweb_rodolf/process_helpers.py
cubicweb_rodolf/schema.py
cubicweb_rodolf/views.py
cubicweb_rodolf/workflows.py
cubicweb_rodolf/i18n/en.po
cubicweb_rodolf/i18n/es.po
cubicweb_rodolf/i18n/fr.po
cubicweb_rodolf/migration/0.1.1_Any.py
cubicweb_rodolf/migration/0.1.2_Any.py
cubicweb_rodolf/migration/0.11.0_Any.py
cubicweb_rodolf/migration/0.11.3_Any.py
cubicweb_rodolf/migration/0.2.0_Any.py
cubicweb_rodolf/migration/0.4.0_Any.py
cubicweb_rodolf/migration/0.5.0_Any.py
cubicweb_rodolf/migration/0.6.0_Any.py
cubicweb_rodolf/migration/0.7.1_Any.py
cubicweb_rodolf/migration/0.8.0_Any.py
cubicweb_rodolf/migration/0.8.2_Any.py
cubicweb_rodolf/migration/0.9.0_Any.py
cubicweb_rodolf/migration/postcreate.py
cubicweb_rodolf/sobjects/__init__.py
cubicweb_rodolf/sobjects/process_type_registry.py
cubicweb_rodolf/sobjects/task_type_registry.py
cubicweb_rodolf-0.12.0.dist-info/LICENSE.md
cubicweb_rodolf-0.12.0.dist-info/METADATA
cubicweb_rodolf-0.12.0.dist-info/WHEEL
cubicweb_rodolf-0.12.0.dist-info/entry_points.txt
cubicweb_rodolf-0.12.0.dist-info/top_level.txt
cubicweb_rodolf-0.12.0.dist-info/RECORD
