Metadata-Version: 2.1
Name: cubicweb-rodolf
Version: 0.12.0
Summary: RDF data production monitoring (RODOLF)
Home-page: https://forge.extranet.logilab.fr/cubicweb/cubes/rodolf
Author: LOGILAB S.A. (Paris, FRANCE)
Author-email: contact@logilab.fr
License: LGPL
Classifier: Environment :: Web Environment
Classifier: Framework :: CubicWeb
Classifier: Programming Language :: Python :: 3
Classifier: Programming Language :: JavaScript
License-File: LICENSE.md
Requires-Dist: cubicweb[postgresql,s3]<5.0.0,>=4.6.3
Requires-Dist: cubicweb-api<0.16.0,>=0.15.0
Requires-Dist: cubicweb-file<5.0.0,>=4.1.0
Requires-Dist: cubicweb-oauth2
Requires-Dist: rql<1.0.0,>=0.43.2
Requires-Dist: cubicweb-rq
Requires-Dist: cubicweb-s3storage
Requires-Dist: requests
Requires-Dist: pyshacl
Requires-Dist: Jinja2
Requires-Dist: rdf-data-manager
Requires-Dist: tqdm
Requires-Dist: pyyaml
Provides-Extra: dev
Requires-Dist: fakeredis; extra == "dev"
Requires-Dist: requests-mock; extra == "dev"
Requires-Dist: moto; extra == "dev"
